{
  "name": "Solar System Name Generator",
  "description": "Blast off into a universe of awesome names! Need a cool moniker inspired by the cosmos? Our Solar System Name Generator is your ticket to the stars. Discover names that are out of this world!",
  "slug": "solar-system-name-generator",
  "icon": "\ud83e\ude90",
  "introduction": "Ever dreamed of having a name as epic as Jupiter or as mysterious as Pluto? You've come to the right place! Our Solar System Name Generator combines celestial elements to create unique and captivating names. Perfect for characters, projects, or just plain fun!",
  "howToUse": [
    "Simply click the 'Generate' button, and *poof*! A brand-new, cosmically cool name will appear.",
    "Feeling picky? Keep clicking! There are billions of potential combinations, so you're bound to find the perfect fit.",
    "Want something *really* special? Play around with different prefixes and suffixes until you stumble upon a name that resonates with your inner astronaut.",
    "Share your stellar find with your friends and family. Prepare to be showered with compliments on your newfound cosmic identity!",
    "Use it wisely! With great name comes great responsibility... maybe."
  ],
  "faqs": [
    {
      "question": "What kind of names does this generator create?",
      "answer": "This generator creates names inspired by planets, moons, constellations, and other celestial bodies in our solar system. Expect a blend of scientific accuracy and creative flair!"
    },
    {
      "question": "Can I use these names for my science fiction novel?",
      "answer": "Absolutely! In fact, we encourage it. Let your imagination run wild and populate your universe with these stellar names."
    },
    {
      "question": "Are the names generated scientifically accurate?",
      "answer": "While we strive for a cosmic vibe, some names might be more creative than scientifically precise. Think of it as 'science-inspired' rather than 'science-textbook'."
    },
    {
      "question": "How many names can I generate?",
      "answer": "As many as your heart desires! There's no limit to the number of names you can create. Keep clicking until you find the perfect one (or several!)."
    },
    {
      "question": "Can I suggest new prefixes or suffixes for the generator?",
      "answer": "We'd love to hear your ideas! Send us your suggestions through our contact form, and we'll consider adding them to the generator. Help us expand the cosmos of names!"
    },
    {
      "question": "Is this generator free to use?",
      "answer": "Yes, absolutely! Our Solar System Name Generator is completely free for you to use. Enjoy exploring the universe of names!"
    }
  ],
  "prefixes": [
    "Astro",
    "Cosmo",
    "Terra",
    "Sol",
    "Luna",
    "Mars",
    "Venus",
    "Jupiter",
    "Saturn",
    "Uranus",
    "Neptu",
    "Pluto",
    "Gala",
    "Nova",
    "Orion",
    "Andro",
    "Celes",
    "Equi",
    "Stella",
    "Titan",
    "Io",
    "Europa",
    "Gany",
    "Calli",
    "Rhea",
    "Dione",
    "Tethys",
    "Encela",
    "Mima",
    "Hyper",
    "Iapetus",
    "Phobos",
    "Deimos",
    "Charon",
    "Eris",
    "Make",
    "Haume",
    "Sedna"
  ],
  "suffixes": [
    "on",
    "a",
    "ar",
    "is",
    "ia",
    "ex",
    "ix",
    "yx",
    "os",
    "us",
    "an",
    "en",
    "in",
    "yn",
    "al",
    "el",
    "il",
    "yl",
    "ar",
    "er",
    "ir",
    "yr",
    "es",
    "ys",
    "om",
    "um",
    "im",
    "ym",
    "id",
    "od",
    "ed",
    "yd",
    "ta",
    "te",
    "ti",
    "to",
    "tu",
    "cy",
    "sy",
    "ly",
    "ry",
    "ny",
    "my",
    "by",
    "py",
    "ty",
    "xy",
    "zy",
    "vi"
  ]
}